{
  "_class": "symbolMaster",
  "backgroundColor": {
    "_class": "color",
    "alpha": 1,
    "blue": 1,
    "green": 1,
    "red": 1
  },
  "booleanOperation": -1,
  "changeIdentifier": 214,
  "clippingMaskMode": 0,
  "do_objectID": "31CE7F68-34B6-4937-81F5-E94290BEBC5B",
  "exportOptions": {
    "_class": "exportOptions",
    "exportFormats": [
    ],
    "includedLayerIds": [
    ],
    "layerOptions": 0,
    "shouldTrim": false
  },
  "frame": {
    "_class": "rect",
    "constrainProportions": false,
    "height": 469,
    "width": 1440,
    "x": 4278,
    "y": 3185
  },
  "hasBackgroundColor": false,
  "hasClickThrough": true,
  "hasClippingMask": false,
  "horizontalRulerData": {
    "_class": "rulerData",
    "base": 0,
    "guides": [
    ]
  },
  "includeBackgroundColorInExport": true,
  "includeBackgroundColorInInstance": false,
  "includeInCloudUpload": true,
  "isFixedToViewport": false,
  "isFlippedHorizontal": false,
  "isFlippedVertical": false,
  "isFlowHome": false,
  "isLocked": false,
  "isVisible": true,
  "layerListExpandedType": 0,
  "layers": [
    {
      "class": "rectangle",
      "id": "4746BF31-712A-499F-92D6-FA38A669E5BF"
    }
  ],
  "name": "W MOLECULE : HEADER",
  "nameIsFixed": true,
  "resizesContent": false,
  "resizingConstraint": 63,
  "resizingType": 0,
  "rotation": 0,
  "shouldBreakMaskChain": true,
  "style": {
    "_class": "style",
    "endMarkerType": 0,
    "miterLimit": 10,
    "startMarkerType": 0,
    "windingRule": 1
  },
  "symbolID": "7129202D-F60E-4B5B-94E7-CDE0263B494D",
  "verticalRulerData": {
    "_class": "rulerData",
    "base": 0,
    "guides": [
    ]
  }
}