{
  "_class": "symbolInstance",
  "booleanOperation": -1,
  "clippingMaskMode": 0,
  "do_objectID": "88FA4E1B-A54F-4A5E-9245-E72CCE904B66",
  "exportOptions": {
    "_class": "exportOptions",
    "do_objectID": "CA1D5491-4CE6-4C84-801F-7AF6ED411205",
    "exportFormats": [
    ],
    "includedLayerIds": [
    ],
    "layerOptions": 0,
    "shouldTrim": false
  },
  "frame": {
    "_class": "rect",
    "constrainProportions": false,
    "do_objectID": "F2F0794D-00C3-4D82-BD54-22AB54D133EF",
    "height": 18,
    "width": 18,
    "x": 90,
    "y": 367
  },
  "hasClippingMask": false,
  "horizontalSpacing": 0,
  "isFixedToViewport": false,
  "isFlippedHorizontal": false,
  "isFlippedVertical": false,
  "isLocked": false,
  "isVisible": true,
  "layerListExpandedType": 0,
  "name": "P MOLECULE : SOCIAL ICON Copy 3",
  "nameIsFixed": false,
  "overrideValues": [
  ],
  "resizingConstraint": 63,
  "resizingType": 0,
  "rotation": 0,
  "scale": 1,
  "shouldBreakMaskChain": false,
  "style": {
    "_class": "style",
    "do_objectID": "04022E77-D5AC-4A41-B8DF-A43B26DFDFE6",
    "endMarkerType": 0,
    "miterLimit": 10,
    "startMarkerType": 0,
    "windingRule": 1
  },
  "symbolID": "81270B84-85C6-4E2C-969D-FCFE472BBFA0",
  "verticalSpacing": 0
}