{
  "_class": "symbolInstance",
  "booleanOperation": -1,
  "clippingMaskMode": 0,
  "do_objectID": "71E3CA8E-1324-4695-AA60-2BE0D6E6A0F5",
  "exportOptions": {
    "_class": "exportOptions",
    "do_objectID": "AE7305DC-0062-4BA2-8595-96A76D1C0B60",
    "exportFormats": [
    ],
    "includedLayerIds": [
    ],
    "layerOptions": 0,
    "shouldTrim": false
  },
  "frame": {
    "_class": "rect",
    "constrainProportions": false,
    "do_objectID": "566B7F66-BDB9-404D-AC89-34BF6BB1B106",
    "height": 80,
    "width": 80,
    "x": 73,
    "y": 1670
  },
  "hasClippingMask": false,
  "horizontalSpacing": 0,
  "isFixedToViewport": false,
  "isFlippedHorizontal": false,
  "isFlippedVertical": false,
  "isLocked": false,
  "isVisible": true,
  "layerListExpandedType": 0,
  "name": "MOLECULE : ICON",
  "nameIsFixed": false,
  "overrideValues": [
  ],
  "resizingConstraint": 63,
  "resizingType": 0,
  "rotation": 0,
  "scale": 1,
  "shouldBreakMaskChain": false,
  "style": {
    "_class": "style",
    "do_objectID": "2237D2FA-AEC7-4949-AE6C-71DB5DC521A6",
    "endMarkerType": 0,
    "miterLimit": 10,
    "startMarkerType": 0,
    "windingRule": 1
  },
  "symbolID": "E0DBBF9E-14C9-4C75-9B25-5FFEEC728584",
  "verticalSpacing": 0
}