{
  "_class": "symbolInstance",
  "booleanOperation": -1,
  "clippingMaskMode": 0,
  "do_objectID": "1440F80F-2232-472D-8CFD-B39958DD7929",
  "exportOptions": {
    "_class": "exportOptions",
    "do_objectID": "F2FE2576-B768-4050-9C84-4CAFAA221A80",
    "exportFormats": [
    ],
    "includedLayerIds": [
    ],
    "layerOptions": 0,
    "shouldTrim": false
  },
  "frame": {
    "_class": "rect",
    "constrainProportions": false,
    "do_objectID": "C8B527E0-8DCB-4CDA-8723-0E7375463BB1",
    "height": 79,
    "width": 320,
    "x": 0,
    "y": 836
  },
  "hasClippingMask": false,
  "horizontalSpacing": 0,
  "isFixedToViewport": false,
  "isFlippedHorizontal": false,
  "isFlippedVertical": false,
  "isLocked": false,
  "isVisible": true,
  "layerListExpandedType": 0,
  "name": "P MOLECULE : FOOTER",
  "nameIsFixed": false,
  "overrideValues": [
  ],
  "resizingConstraint": 63,
  "resizingType": 0,
  "rotation": 0,
  "scale": 1,
  "shouldBreakMaskChain": false,
  "style": {
    "_class": "style",
    "do_objectID": "566CCFD8-6412-40C7-9801-1E003D74E3EB",
    "endMarkerType": 0,
    "miterLimit": 10,
    "startMarkerType": 0,
    "windingRule": 1
  },
  "symbolID": "F05C8D08-237C-4EF2-B5ED-29B1ABEED48D",
  "verticalSpacing": 0
}