{
  "_class": "group",
  "booleanOperation": -1,
  "clippingMaskMode": 0,
  "do_objectID": "BA5A17BB-BE16-4710-9B17-032F0158E7BD",
  "exportOptions": {
    "_class": "exportOptions",
    "do_objectID": "C3835C1C-92F9-4848-9552-B9CFCD9F8CE9",
    "exportFormats": [
    ],
    "includedLayerIds": [
    ],
    "layerOptions": 0,
    "shouldTrim": false
  },
  "frame": {
    "_class": "rect",
    "constrainProportions": false,
    "do_objectID": "CA4A9FDB-375B-4150-A60C-6BC564A43814",
    "height": 219,
    "width": 838,
    "x": 541,
    "y": 1414
  },
  "hasClickThrough": false,
  "hasClippingMask": false,
  "isFixedToViewport": false,
  "isFlippedHorizontal": false,
  "isFlippedVertical": false,
  "isLocked": false,
  "isVisible": true,
  "layerListExpandedType": 0,
  "layers": [
    {
      "class": "rectangle",
      "id": "B58C1E06-00B1-43A1-8BB4-560A41B08ED6"
    },
    {
      "class": "text",
      "id": "A9F3A811-4DAD-4794-B266-AAA148AEF4DD"
    }
  ],
  "name": "molecule : footer text copy 3",
  "nameIsFixed": false,
  "resizingConstraint": 63,
  "resizingType": 0,
  "rotation": 0,
  "shouldBreakMaskChain": false,
  "style": {
    "_class": "style",
    "do_objectID": "B67DFCC3-3D2B-4C7A-BEF6-DA94AF3F3E4E",
    "endMarkerType": 0,
    "miterLimit": 10,
    "startMarkerType": 0,
    "windingRule": 1
  }
}