{
  "_class": "symbolInstance",
  "booleanOperation": -1,
  "clippingMaskMode": 0,
  "do_objectID": "2B30B4F9-3AF0-4489-A757-1D72160CF7D6",
  "exportOptions": {
    "_class": "exportOptions",
    "do_objectID": "1DE1A9E1-6172-4D89-A50C-62202D2A3B76",
    "exportFormats": [
    ],
    "includedLayerIds": [
    ],
    "layerOptions": 0,
    "shouldTrim": false
  },
  "frame": {
    "_class": "rect",
    "constrainProportions": false,
    "do_objectID": "7102D428-3DEE-4923-B42C-0BB7606CB470",
    "height": 120.1258609505421,
    "width": 157,
    "x": 653,
    "y": 0
  },
  "hasClippingMask": false,
  "horizontalSpacing": 0,
  "isFixedToViewport": false,
  "isFlippedHorizontal": false,
  "isFlippedVertical": false,
  "isLocked": false,
  "isVisible": true,
  "layerListExpandedType": 0,
  "name": "MOLECULE : BUTTON Copy",
  "nameIsFixed": false,
  "overrideValues": [
    {
      "_class": "overrideValue",
      "do_objectID": "34A7A394-8B90-49E3-AF1D-048B465A1B06",
      "overrideName": "F5C59088-5363-4722-9BA2-881FBB02923D_stringValue",
      "value": "DEGREE OPTIONS"
    }
  ],
  "resizingConstraint": 63,
  "resizingType": 0,
  "rotation": 0,
  "scale": 1,
  "shouldBreakMaskChain": false,
  "style": {
    "_class": "style",
    "do_objectID": "BD50171D-BBD7-45AC-AF48-BD67AA211062",
    "endMarkerType": 0,
    "miterLimit": 10,
    "startMarkerType": 0,
    "windingRule": 1
  },
  "symbolID": "F1362180-D0B2-401F-BCB8-AA47B13EEE22",
  "userInfo": {
    "com.invision.prototype": {
      "backgroundOpacity": 0,
      "closeOnClickOutside": 1,
      "componentType": "SRLink",
      "fixOverlayPosition": 1,
      "gesture": 0,
      "linkType": 0,
      "maintainScrollPositionAfterGesture": 0,
      "maintainScrollPositionAfterRedirect": 0,
      "openURLInNewWindow": 0,
      "overlayPosition": 0,
      "overlayTransition": 0,
      "redirectAfter": 0,
      "reverseTransitionOnClose": 1,
      "scrollToPosition": 0,
      "smoothScrolling": 0,
      "stayOnTargetScreen": 0,
      "targetArtboardID": "8672381A-CEE3-412C-A5EB-FE0C3BA6FA4B",
      "transition": 0
    }
  },
  "verticalSpacing": 0
}