{
  "_class": "symbolInstance",
  "booleanOperation": -1,
  "clippingMaskMode": 0,
  "do_objectID": "A006BCF4-E0D0-49FC-ADCA-823C76E06E3F",
  "exportOptions": {
    "_class": "exportOptions",
    "do_objectID": "007602C0-E8D7-4A68-B9C4-CD5C82A9A314",
    "exportFormats": [
    ],
    "includedLayerIds": [
    ],
    "layerOptions": 0,
    "shouldTrim": false
  },
  "frame": {
    "_class": "rect",
    "constrainProportions": false,
    "do_objectID": "DFF93BD9-F19E-472E-89D8-7A8C08FEF6CB",
    "height": 80.08390730036149,
    "width": 80,
    "x": 301,
    "y": 1684.765199831353
  },
  "hasClippingMask": false,
  "horizontalSpacing": 0,
  "isFixedToViewport": false,
  "isFlippedHorizontal": false,
  "isFlippedVertical": false,
  "isLocked": false,
  "isVisible": true,
  "layerListExpandedType": 0,
  "name": "MOLECULE : ICON Copy 2",
  "nameIsFixed": false,
  "overrideValues": [
  ],
  "resizingConstraint": 63,
  "resizingType": 0,
  "rotation": 0,
  "scale": 1,
  "shouldBreakMaskChain": false,
  "style": {
    "_class": "style",
    "do_objectID": "46496427-BFE7-41FD-86B1-5386DB4DAB2F",
    "endMarkerType": 0,
    "miterLimit": 10,
    "startMarkerType": 0,
    "windingRule": 1
  },
  "symbolID": "97FF0EF6-AA75-4BF8-8646-8926CC480869",
  "verticalSpacing": 0
}