{
  "_class": "symbolInstance",
  "booleanOperation": -1,
  "clippingMaskMode": 0,
  "do_objectID": "693FA3C0-2AC4-47C5-A799-1E5740D8A7C1",
  "exportOptions": {
    "_class": "exportOptions",
    "do_objectID": "1310250E-8DFD-4EB0-BAB0-DE105D1722E9",
    "exportFormats": [
    ],
    "includedLayerIds": [
    ],
    "layerOptions": 0,
    "shouldTrim": false
  },
  "frame": {
    "_class": "rect",
    "constrainProportions": false,
    "do_objectID": "2BA73C0C-F1CB-4F88-839E-111A9579943D",
    "height": 24,
    "width": 112,
    "x": 1,
    "y": 181
  },
  "hasClippingMask": false,
  "horizontalSpacing": 0,
  "isFixedToViewport": false,
  "isFlippedHorizontal": false,
  "isFlippedVertical": false,
  "isLocked": false,
  "isVisible": true,
  "layerListExpandedType": 0,
  "name": "P MOLECULE : BUTTON Copy 4",
  "nameIsFixed": false,
  "overrideValues": [
    {
      "_class": "overrideValue",
      "do_objectID": "BCDEB41F-A9D4-4093-9C2D-BB7DF6BBEFF7",
      "overrideName": "8121E2A9-48FE-4F03-8CD6-3037979E4F5E_stringValue",
      "value": "STUDENT HIGHLIGHT"
    }
  ],
  "resizingConstraint": 63,
  "resizingType": 0,
  "rotation": 0,
  "scale": 1,
  "shouldBreakMaskChain": false,
  "style": {
    "_class": "style",
    "do_objectID": "5A652DE9-13ED-4C3B-9F5B-D123C99FF09F",
    "endMarkerType": 0,
    "miterLimit": 10,
    "startMarkerType": 0,
    "windingRule": 1
  },
  "symbolID": "5F085EE4-29A6-4D40-8355-BE132A2EE6E9",
  "userInfo": {
    "com.invision.prototype": {
      "backgroundOpacity": 0,
      "closeOnClickOutside": 1,
      "componentType": "SRLink",
      "fixOverlayPosition": 1,
      "gesture": 0,
      "linkType": 0,
      "maintainScrollPositionAfterGesture": 0,
      "maintainScrollPositionAfterRedirect": 0,
      "openURLInNewWindow": 0,
      "overlayPosition": 0,
      "overlayTransition": 0,
      "redirectAfter": 0,
      "reverseTransitionOnClose": 1,
      "scrollToPosition": 0,
      "smoothScrolling": 0,
      "stayOnTargetScreen": 0,
      "targetArtboardID": "09494206-C974-4826-A694-2A4035587D3D",
      "transition": 0
    }
  },
  "verticalSpacing": 0
}