{
  "_class": "symbolInstance",
  "booleanOperation": -1,
  "clippingMaskMode": 0,
  "do_objectID": "49B1B308-4AD2-49D7-AE84-C7ED0B85176F",
  "exportOptions": {
    "_class": "exportOptions",
    "do_objectID": "D7D0B746-E6DA-440D-AC22-9EF906BC0277",
    "exportFormats": [
    ],
    "includedLayerIds": [
    ],
    "layerOptions": 0,
    "shouldTrim": false
  },
  "frame": {
    "_class": "rect",
    "constrainProportions": false,
    "do_objectID": "B2BB0A31-D5B4-47F0-9219-0DCEBA9166F1",
    "height": 18,
    "width": 18,
    "x": 15,
    "y": 520
  },
  "hasClippingMask": false,
  "horizontalSpacing": 0,
  "isFixedToViewport": false,
  "isFlippedHorizontal": false,
  "isFlippedVertical": false,
  "isLocked": false,
  "isVisible": true,
  "layerListExpandedType": 0,
  "name": "P MOLECULE : SOCIAL ICON",
  "nameIsFixed": false,
  "overrideValues": [
  ],
  "resizingConstraint": 63,
  "resizingType": 0,
  "rotation": 0,
  "scale": 1,
  "shouldBreakMaskChain": false,
  "style": {
    "_class": "style",
    "do_objectID": "5C3D3EEC-3A86-4341-A491-6946E7505484",
    "endMarkerType": 0,
    "miterLimit": 10,
    "startMarkerType": 0,
    "windingRule": 1
  },
  "symbolID": "5A311BB9-3E45-4D44-967D-C12D9B7F72F4",
  "verticalSpacing": 0
}