{
  "_class": "symbolInstance",
  "booleanOperation": -1,
  "clippingMaskMode": 0,
  "do_objectID": "50701F28-C16C-46C0-B77C-C61C1D22B7C2",
  "exportOptions": {
    "_class": "exportOptions",
    "do_objectID": "4A59012B-852A-413F-BAE4-B51125BF5C3A",
    "exportFormats": [
    ],
    "includedLayerIds": [
    ],
    "layerOptions": 0,
    "shouldTrim": false
  },
  "frame": {
    "_class": "rect",
    "constrainProportions": false,
    "do_objectID": "C977BDE9-131E-48A6-A29B-60B5476D25CB",
    "height": 328,
    "width": 603,
    "x": 838,
    "y": 134
  },
  "hasClippingMask": false,
  "horizontalSpacing": 0,
  "isFixedToViewport": false,
  "isFlippedHorizontal": false,
  "isFlippedVertical": false,
  "isLocked": false,
  "isVisible": true,
  "layerListExpandedType": 0,
  "name": "MOLECULE : TITLE",
  "nameIsFixed": false,
  "overrideValues": [
  ],
  "resizingConstraint": 63,
  "resizingType": 0,
  "rotation": 0,
  "scale": 1,
  "shouldBreakMaskChain": false,
  "style": {
    "_class": "style",
    "do_objectID": "632AC004-8B20-4E56-BC91-F19A3D341982",
    "endMarkerType": 0,
    "miterLimit": 10,
    "startMarkerType": 0,
    "windingRule": 1
  },
  "symbolID": "336E0F50-B26E-4D80-AF0C-E65664BCC0DB",
  "verticalSpacing": 0
}