{
  "_class": "symbolInstance",
  "booleanOperation": -1,
  "clippingMaskMode": 0,
  "do_objectID": "D84F11DD-BEA5-424C-A0C1-F5E89EDB5CFB",
  "exportOptions": {
    "_class": "exportOptions",
    "do_objectID": "F7B2B536-D151-4BCA-9C01-280EB67AD52A",
    "exportFormats": [
    ],
    "includedLayerIds": [
    ],
    "layerOptions": 0,
    "shouldTrim": false
  },
  "frame": {
    "_class": "rect",
    "constrainProportions": false,
    "do_objectID": "93B5CA58-2559-41FD-A615-C2A337E7EBE0",
    "height": 80,
    "width": 80,
    "x": 73,
    "y": 1670
  },
  "hasClippingMask": false,
  "horizontalSpacing": 0,
  "isFixedToViewport": false,
  "isFlippedHorizontal": false,
  "isFlippedVertical": false,
  "isLocked": false,
  "isVisible": true,
  "layerListExpandedType": 0,
  "name": "MOLECULE : ICON",
  "nameIsFixed": false,
  "overrideValues": [
  ],
  "resizingConstraint": 63,
  "resizingType": 0,
  "rotation": 0,
  "scale": 1,
  "shouldBreakMaskChain": false,
  "style": {
    "_class": "style",
    "do_objectID": "E687908A-281B-415F-BB2A-0B8B01A82AC9",
    "endMarkerType": 0,
    "miterLimit": 10,
    "startMarkerType": 0,
    "windingRule": 1
  },
  "symbolID": "E0DBBF9E-14C9-4C75-9B25-5FFEEC728584",
  "verticalSpacing": 0
}