{
  "_class": "symbolInstance",
  "booleanOperation": -1,
  "clippingMaskMode": 0,
  "do_objectID": "DE10537A-D4C7-4EEA-85C0-9CB3243FBFEB",
  "exportOptions": {
    "_class": "exportOptions",
    "do_objectID": "BFCDAF0B-56F9-4B62-8B13-F177F163ED36",
    "exportFormats": [
    ],
    "includedLayerIds": [
    ],
    "layerOptions": 0,
    "shouldTrim": false
  },
  "frame": {
    "_class": "rect",
    "constrainProportions": false,
    "do_objectID": "1405DAB2-B5A1-48D8-89C6-8EA6EDC67A5C",
    "height": 186.1950844733403,
    "width": 79,
    "x": 722,
    "y": 1209.267000235458
  },
  "hasClippingMask": false,
  "horizontalSpacing": 0,
  "isFixedToViewport": false,
  "isFlippedHorizontal": false,
  "isFlippedVertical": false,
  "isLocked": false,
  "isVisible": true,
  "layerListExpandedType": 0,
  "name": "W MOLECULE: SLIDE ARROW LEFT",
  "nameIsFixed": false,
  "overrideValues": [
  ],
  "resizingConstraint": 63,
  "resizingType": 0,
  "rotation": 0,
  "scale": 1,
  "shouldBreakMaskChain": false,
  "style": {
    "_class": "style",
    "do_objectID": "4D6FAC80-0184-41F7-87CE-E431A2E6744A",
    "endMarkerType": 0,
    "miterLimit": 10,
    "startMarkerType": 0,
    "windingRule": 1
  },
  "symbolID": "B206F7D4-6AD9-4391-AEA7-00A2A8BA12A6",
  "userInfo": {
  },
  "verticalSpacing": 0
}