{
  "_class": "group",
  "booleanOperation": -1,
  "clippingMaskMode": 0,
  "do_objectID": "3780D44B-7342-419D-92A4-D385B946F6B8",
  "exportOptions": {
    "_class": "exportOptions",
    "do_objectID": "6493AC63-7B15-49BB-B4BA-538C9D4243D9",
    "exportFormats": [
    ],
    "includedLayerIds": [
    ],
    "layerOptions": 0,
    "shouldTrim": false
  },
  "frame": {
    "_class": "rect",
    "constrainProportions": false,
    "do_objectID": "57735BAD-C885-4B16-A5FE-9D743007976D",
    "height": 81,
    "width": 150,
    "x": 160,
    "y": 0
  },
  "hasClickThrough": false,
  "hasClippingMask": false,
  "isFixedToViewport": false,
  "isFlippedHorizontal": false,
  "isFlippedVertical": false,
  "isLocked": false,
  "isVisible": true,
  "layerListExpandedType": 1,
  "layers": [
    {
      "class": "symbolInstance",
      "id": "D380C331-680B-4F61-BA61-5AABDB3A640A"
    }
  ],
  "name": "molecule : footer text copy 3",
  "nameIsFixed": false,
  "resizingConstraint": 63,
  "resizingType": 0,
  "rotation": 0,
  "shouldBreakMaskChain": false,
  "style": {
    "_class": "style",
    "do_objectID": "7C63809B-FF90-4A3E-8790-524E63B0A600",
    "endMarkerType": 0,
    "miterLimit": 10,
    "startMarkerType": 0,
    "windingRule": 1
  }
}